Metadata-Version: 1.1
Name: kslabs-scrapy-heroku
Version: 0.7.1
Summary: Utilities for running scrapy on heroku
Home-page: https://github.com/Keystone-Strategy/kslabs-scrapy-heroku
Author: Dave McLain
Author-email: dave@trainca.se
License: BSD
Keywords: scrapy,heroku
Platform: UNKNOWN
Classifier: Development Status :: 4 - Beta
Classifier: Intended Audience :: Developers
Classifier: License :: OSI Approved :: BSD License
Classifier: Operating System :: OS Independent
Classifier: Programming Language :: Python
Classifier: Topic :: Internet :: WWW/HTTP
